konfluence/__init__.py
konfluence/admin.py
konfluence/core.py
konfluence/models.py
konfluence/migrations/0001_initial.py
konfluence/migrations/0002_item_active.py
konfluence/migrations/__init__.py
konfluence-0.0.5.dist-info/DESCRIPTION.rst
konfluence-0.0.5.dist-info/METADATA
konfluence-0.0.5.dist-info/RECORD
konfluence-0.0.5.dist-info/WHEEL
konfluence-0.0.5.dist-info/metadata.json
konfluence-0.0.5.dist-info/top_level.txt
tests/__init__.py
tests/test_konf.py
