Metadata-Version: 2.0
Name: konfluence
Version: 0.0.5
Summary: A conf system
Home-page: https://github.com/claydodo/konfluence
Author: claydodo and his little friends (xiao huo ban)
Author-email: claydodo@foxmail.com
License: UNKNOWN
Platform: UNKNOWN
Classifier: Programming Language :: Python :: 2.7 
Classifier: Operating System :: OS Independent
Requires-Dist: six
Requires-Dist: krux
Requires-Dist: krust
